__init__.py
alibabacloud_rds_openapi_mcp_server/__init__.py
alibabacloud_rds_openapi_mcp_server/db_service.py
alibabacloud_rds_openapi_mcp_server/server.py
alibabacloud_rds_openapi_mcp_server/utils.py
alibabacloud_rds_openapi_mcp_server/core/__init__.py
alibabacloud_rds_openapi_mcp_server/core/context.py
alibabacloud_rds_openapi_mcp_server/core/mcp.py
alibabacloud_rds_openapi_mcp_server/prompts/__init__.py
alibabacloud_rds_openapi_mcp_server/prompts/system_prompts.py
alibabacloud_rds_openapi_mcp_server/tools/__init__.py
alibabacloud_rds_openapi_mcp_server/tools/aliyun_openapi_gateway.py
alibabacloud_rds_openapi_mcp_server/tools/rds_custom_action.py
alibabacloud_rds_openapi_mcp_server/tools/rds_custom_read.py
alibabacloud_rds_openapi_mcp_server-3.0.9.dist-info/licenses/LICENSE
alibabacloud_rds_openapi_mcp_server-3.0.9.dist-info/METADATA
alibabacloud_rds_openapi_mcp_server-3.0.9.dist-info/WHEEL
alibabacloud_rds_openapi_mcp_server-3.0.9.dist-info/entry_points.txt
alibabacloud_rds_openapi_mcp_server-3.0.9.dist-info/top_level.txt
alibabacloud_rds_openapi_mcp_server-3.0.9.dist-info/RECORD
