Metadata-Version: 2.4
Name: alibabacloud-rds-openapi-mcp-server
Version: 3.0.9
Summary: MCP server for RDS Services via OPENAPI.
Author: AlibabaCloud RDS
License-Expression: Apache-2.0
Project-URL: Homepage, https://github.com/aliyun/alibabacloud-rds-openapi-mcp-server
Project-URL: Documentation, https://github.com/aliyun/alibabacloud-rds-openapi-mcp-server/
Project-URL: Source, https://github.com/aliyun/alibabacloud-rds-openapi-mcp-server.git
Project-URL: Bug Tracker, https://github.com/aliyun/alibabacloud-rds-openapi-mcp-server/issues
Requires-Python: >=3.12
License-File: LICENSE
Requires-Dist: alibabacloud-bssopenapi20171214>=5.0.0
Requires-Dist: alibabacloud-das20200116==2.7.1
Requires-Dist: alibabacloud-rds20140815>=11.0.0
Requires-Dist: alibabacloud-vpc20160428>=6.11.4
Requires-Dist: httpx>=0.28.1
Requires-Dist: mcp[cli]>=1.10.1
Requires-Dist: pymysql>=1.1.1
Requires-Dist: pyodbc>=5.2.0
Dynamic: license-file
